test_imports/__init__.py
test_imports/exceptions.py
test_imports/interfaces.py
test_imports/states.py
test_imports/types.py
test_imports/utils.py
test_imports/version.py
test_imports/worker.py
test_imports-1.0.2.dist-info/METADATA
test_imports-1.0.2.dist-info/WHEEL
test_imports-1.0.2.dist-info/RECORD
