Metadata-Version: 2.1
Name: test-imports
Version: 1.0.2
Summary: A Python package for failing and mocking imports in automated tests
Project-URL: Homepage, https://github.com/vsego/test-imports
Project-URL: Bug Tracker, https://github.com/vsego/test-imports/issues
Project-URL: Changelog, https://github.com/vsego/test-imports/blob/master/CHANGELOG.md
Author-email: Vedran Sego <vsego@vsego.org>
License-Expression: MIT
Keywords: import,mock,test
Classifier: Operating System :: OS Independent
Classifier: Programming Language :: Python :: 3.11
Classifier: Programming Language :: Python :: 3.12
Classifier: Typing :: Typed
Requires-Python: >=3.11
Requires-Dist: mypy-extensions
